adrubix_jmp/__init__.py
adrubix_jmp/_version.py
adrubix_jmp/rubixheatmap.py
tests/__init__.py
tests/conftest.py
tests/test_adrubix.py
adrubix_jmp-0.1.30.dist-info/LICENSE
adrubix_jmp-0.1.30.dist-info/METADATA
adrubix_jmp-0.1.30.dist-info/WHEEL
adrubix_jmp-0.1.30.dist-info/top_level.txt
adrubix_jmp-0.1.30.dist-info/RECORD
