Metadata-Version: 2.1
Name: adrubix-jmp
Version: 0.1.30
Summary: RubixHeatmap class for plotting complex, highly customizable heatmaps with metadata as HTML and PNG
Home-page: https://github.com/Advestis/adrubix_jmp
Author: Advestis
Author-email: pythondev@advestis.com
License: GPLv3
Project-URL: Bug Tracker, https://github.com/Advestis/adrubix_jmp/issues
Project-URL: Documentation, https://advestis.github.io/adrubix_jmp
Project-URL: Source Code, https://github.com/Advestis/adrubix_jmp/
Classifier: Development Status :: 5 - Production/Stable
Classifier: Operating System :: Unix
Classifier: Programming Language :: Python :: 3.7
Classifier: Programming Language :: Python :: 3.8
Classifier: Programming Language :: Python :: 3.9
Requires-Python: >=3.7
License-File: LICENSE
Requires-Dist: pandas (~=1.4)
Requires-Dist: bokeh (~=2.4)
Requires-Dist: holoviews (~=1.15)
Requires-Dist: panel (~=0.13)
Requires-Dist: html2image (~=2.0)
Requires-Dist: selenium (~=4.4)
Requires-Dist: chromedriver-binary (~=109.0)
Requires-Dist: pytest
